Metadata-Version: 2.1
Name: odoo-addon-stock_location_orderpoint
Version: 18.0.1.0.2
Requires-Python: >=3.10
Requires-Dist: odoo-addon-queue_job==18.0.*
Requires-Dist: odoo-addon-stock_available_base_exclude_location==18.0.*
Requires-Dist: odoo-addon-stock_route_location_source==18.0.*
Requires-Dist: odoo==18.0.*
Summary: Declare orderpoint on a location allowing to replenish any product with the same criteria.
Home-page: https://github.com/OCA/stock-logistics-orderpoint
License: AGPL-3
Author: MT Software, BCIM, Odoo Community Association (OCA)
Author-email: support@odoo-community.org
Classifier: Programming Language :: Python
Classifier: Framework :: Odoo
Classifier: Framework :: Odoo :: 18.0
Classifier: License :: OSI Approved :: GNU Affero General Public License v3
